README.rst
setup.py
jsonchecker/__init__.py
jsonchecker.egg-info/PKG-INFO
jsonchecker.egg-info/SOURCES.txt
jsonchecker.egg-info/dependency_links.txt
jsonchecker.egg-info/entry_points.txt
jsonchecker.egg-info/top_level.txt