Metadata-Version: 1.1
Name: jsonchecker
Version: 0.8.0
Summary: Script that validates JSON files and checks for duplicate keys.
Home-page: https://github.com/legoktm/jsonchecker
Author: Kunal Mehta
Author-email: legoktm@member.fsf.org
License: Public domain
Platform: UNKNOWN
Classifier: License :: Public Domain
Classifier: Development Status :: 5 - Production/Stable
Classifier: Operating System :: OS Independent
Classifier: Intended Audience :: Developers
Classifier: Environment :: Console
Classifier: Programming Language :: Python :: 2.7
Classifier: Programming Language :: Python :: 3
Classifier: Programming Language :: Python :: 3.1
Classifier: Programming Language :: Python :: 3.2
Classifier: Programming Language :: Python :: 3.3
Classifier: Programming Language :: Python :: 3.4
Classifier: Programming Language :: Python :: 3.5
Classifier: Programming Language :: Python :: Implementation :: CPython
Classifier: Programming Language :: Python :: Implementation :: PyPy
Classifier: Programming Language :: Python :: Implementation :: Jython
Classifier: Programming Language :: Python :: Implementation :: Stackless
